nfc_agent/__init__.py
nfc_agent/client.py
nfc_agent/exceptions.py
nfc_agent/poller.py
nfc_agent/py.typed
nfc_agent/types.py
nfc_agent/websocket.py
nfc_agent-0.5.1.dist-info/METADATA
nfc_agent-0.5.1.dist-info/WHEEL
nfc_agent-0.5.1.dist-info/RECORD
