Metadata-Version: 2.4
Name: nfc-agent
Version: 0.5.1
Summary: Python SDK for NFC Agent - read and write NFC cards via local nfc-agent server
Project-URL: Homepage, https://github.com/SimplyPrint/nfc-agent
Project-URL: Documentation, https://github.com/SimplyPrint/nfc-agent/tree/main/sdk/python
Project-URL: Repository, https://github.com/SimplyPrint/nfc-agent
Project-URL: Issues, https://github.com/SimplyPrint/nfc-agent/issues
Author-email: SimplyPrint <support@simplyprint.io>
License-Expression: MIT
Keywords: mifare,nfc,ntag,reader,rfid,simplyprint,smartcard
Classifier: Development Status :: 4 - Beta
Classifier: Intended Audience :: Developers
Classifier: License :: OSI Approved :: MIT License
Classifier: Operating System :: OS Independent
Classifier: Programming Language :: Python :: 3
Classifier: Programming Language :: Python :: 3.9
Classifier: Programming Language :: Python :: 3.10
Classifier: Programming Language :: Python :: 3.11
Classifier: Programming Language :: Python :: 3.12
Classifier: Programming Language :: Python :: 3.13
Classifier: Topic :: Software Development :: Libraries :: Python Modules
Classifier: Typing :: Typed
Requires-Python: >=3.9
Requires-Dist: httpx>=0.25.0
Requires-Dist: websockets>=12.0
Provides-Extra: dev
Requires-Dist: mypy>=1.0; extra == 'dev'
Requires-Dist: pytest-asyncio>=0.21; extra == 'dev'
Requires-Dist: pytest-cov>=4.0; extra == 'dev'
Requires-Dist: pytest>=7.0; extra == 'dev'
Requires-Dist: respx>=0.20; extra == 'dev'
Requires-Dist: ruff>=0.1.0; extra == 'dev'
